microdetect/__init__.py
microdetect/cli.py
microdetect/server.py
microdetect/api/__init__.py
microdetect/api/endpoints/__init__.py
microdetect/api/endpoints/annotations.py
microdetect/api/endpoints/datasets.py
microdetect/api/endpoints/hyperparams.py
microdetect/api/endpoints/images.py
microdetect/api/endpoints/inference.py
microdetect/api/endpoints/models.py
microdetect/api/endpoints/system.py
microdetect/api/endpoints/training.py
microdetect/core/__init__.py
microdetect/core/celery_app.py
microdetect/core/config.py
microdetect/core/hyperparam_core.py
microdetect/core/mps_config.py
microdetect/core/training_core.py
microdetect/core/websocket_manager.py
microdetect/core/websocket_utils.py
microdetect/database/__init__.py
microdetect/database/database.py
microdetect/database/migrations/__init__.py
microdetect/database/migrations/env.py
microdetect/database/migrations/script.py.mako
microdetect/database/migrations/versions/3f3c375f19d9_remover_colunas_redundantes_da_tabela_.py
microdetect/database/migrations/versions/4204cd67bb2f_adicionar_coluna_de_classes_ao_modelo_.py
microdetect/database/migrations/versions/444cb2d35019_initial_migration.py
microdetect/database/migrations/versions/48a47757e579_adicionando_todas_as_tabelas_faltantes.py
microdetect/database/migrations/versions/68b6373e8c4f_adicionar_coluna_url_à_tabela_images.py
microdetect/database/migrations/versions/7aa341c085d8_adicionar_índices_na_tabela_dataset_.py
microdetect/database/migrations/versions/7e191d85ab2c_change_url_on_dataset_image.py
microdetect/database/migrations/versions/__init__.py
microdetect/database/migrations/versions/af03f1465b64_adicionar_relação_muitos_para_muitos_.py
microdetect/database/migrations/versions/e1f8f82da258_adicionado_url_no_imagedataset.py
microdetect/database/migrations/versions/eacde9ec6022_criado_annotations.py
microdetect/database/migrations/versions/f004cf6cd85c_add_explicit_bbox_fields_to_annotation.py
microdetect-1.6.3.dist-info/METADATA
microdetect-1.6.3.dist-info/WHEEL
microdetect-1.6.3.dist-info/entry_points.txt
microdetect-1.6.3.dist-info/top_level.txt
microdetect-1.6.3.dist-info/RECORD
