Metadata-Version: 2.4
Name: microdetect
Version: 1.6.3
Summary: Backend Python para detecção de microorganismos
Home-page: https://github.com/suaempresa/microdetect
Author: Sua Empresa
Author-email: contato@empresa.com
Classifier: Programming Language :: Python :: 3
Classifier: License :: OSI Approved :: MIT License
Classifier: Operating System :: OS Independent
Requires-Python: >=3.8
Requires-Dist: fastapi>=0.103.1
Requires-Dist: uvicorn>=0.22.0
Requires-Dist: SQLAlchemy>=2.0.20
Requires-Dist: python-multipart>=0.0.5
Requires-Dist: pillow>=9.0.0
Requires-Dist: numpy>=1.24.0
Requires-Dist: torch>=2.0.0
Requires-Dist: torchvision>=0.15.1
Requires-Dist: scipy>=1.10.0
Requires-Dist: alembic>=1.11.0
Requires-Dist: python-dotenv>=1.0.0
Requires-Dist: psutil>=5.9.5
Requires-Dist: pytz>=2023.3
Requires-Dist: ultralytics>=8.1.0
Requires-Dist: opencv-python>=4.8.0
Requires-Dist: matplotlib>=3.7.0
Requires-Dist: pandas>=2.0.0
Requires-Dist: scikit-learn>=1.3.0
Requires-Dist: requests>=2.32.3
Requires-Dist: GPUtil>=1.4.0
Dynamic: author
Dynamic: author-email
Dynamic: classifier
Dynamic: description
Dynamic: description-content-type
Dynamic: home-page
Dynamic: requires-dist
Dynamic: requires-python
Dynamic: summary
